{
  "header": {
    "date": "lundi 6 juillet 2026 · 20:04 Casablanca",
    "time_casablanca": "lundi 6 juillet 2026 · 20:04 Casablanca",
    "hours_since_morning": 10,
    "morning_time_label": "09h54",
    "since_morning_label": "il y a 10h",
    "win_rate_30d": 100,
    "win_rate_total": "2/2",
    "evening_time_label": "20h02",
    "timing_line": "matin 09h54 · soir 20h02 · Δ10h",
    "ptf_value_delta_since_morning": 41.62,
    "ptf_value_pct_since_morning": 1.53
  },
  "portfolio_snapshot": {
    "value_usd": 2756.26,
    "change_since_morning_pct": 1.53
  },
  "delta_summary": [
    {
      "icon": "⚠",
      "text": "Le marché crypto reste en 'Peur extrême' (F&G 24), mais BTC (+1,3%) et ETH (+1,5%) ont rebondi depuis ce matin, signalant une légère amélioration du sentiment."
    },
    {
      "icon": "✓",
      "text": "Les marchés actions US (S&P 500 +63 pts, Nasdaq +309 pts) ont montré un regain d'appétit pour le risque, contrastant avec la baisse du matin et pouvant soutenir les cryptos à bêta élevé."
    },
    {
      "icon": "⚠",
      "text": "La probabilité de maintien des taux Fed pour juillet a légèrement reculé de 89.5% à 83.5% (Polymarket), introduisant une incertitude sur la politique monétaire future."
    },
    {
      "icon": "✓",
      "text": "Le portefeuille a enregistré un P&L positif de +1.53% depuis ce matin, avec INJ (+6.0%) et IMX (+5.2%) en tête des performances."
    }
  ],
  "market_changes": [
    {
      "status": "unchanged",
      "tag": "Macro",
      "importance": 3,
      "description": "Le Fear & Greed Index reste stable à 24 ('Peur extrême'), confirmant une prudence persistante des investisseurs crypto.",
      "source": "Fear & Greed Index"
    },
    {
      "status": "new",
      "tag": "Macro",
      "importance": 4,
      "description": "Les indices US ont rebondi significativement depuis ce matin, avec le S&P 500 en hausse de 63 points et le Nasdaq de 309 points, signalant un regain d'appétit pour le risque sur les marchés traditionnels.",
      "source": "Yahoo Finance"
    },
    {
      "status": "new",
      "tag": "Catalyseur",
      "importance": 4,
      "description": "Les actions clés du secteur tech et crypto ont affiché de fortes hausses : AMD (+6.87%), TSM (+4.8%), MARA (+3.87%) et COIN (+2.22%), renforçant le sentiment positif pour les actifs liés.",
      "source": "Yahoo Finance"
    },
    {
      "status": "new",
      "tag": "Macro",
      "importance": 3,
      "description": "La probabilité de maintien des taux Fed pour juillet 2026 a reculé de 6 points (de 89.5% à 83.5% sur Polymarket), introduisant une légère incertitude sur la politique monétaire.",
      "source": "Polymarket"
    },
    {
      "status": "confirmed",
      "tag": "Macro",
      "importance": 3,
      "description": "L'or a continué sa progression avec une hausse de 49.8 $ en séance, confirmant son rôle de valeur refuge dans un contexte de prudence globale.",
      "source": "Yahoo Finance"
    }
  ],
  "news_today": [
    {
      "title": "Russia's largest bank plans crypto wallet launch as Moscow clears market path",
      "source": "CoinDesk",
      "time": "11h36",
      "impact": "Potentiellement positif pour l'adoption crypto en Russie, mais l'impact direct sur le marché global reste limité.",
      "status": "actionnable"
    },
    {
      "title": "DeFi protocol Summer.fi halts Lazy Summer vaults after $6 million exploit",
      "source": "CoinDesk",
      "time": "13h42",
      "impact": "Négatif pour le sentiment général autour de la DeFi, mais l'exploit est spécifique à un protocole.",
      "status": "intégré"
    },
    {
      "title": "Top Fed official backs new chair’s rethink of investor communications",
      "source": "Financial Times",
      "time": "16h32",
      "impact": "Indique une volonté d'améliorer la clarté des communications de la Fed, ce qui pourrait réduire l'incertitude future sur les marchés.",
      "status": "intégré"
    },
    {
      "title": "Judge revives fraud claim against Barry Silbert, DCG in Genesis Yield lawsuit",
      "source": "The Block",
      "time": "18h55",
      "impact": "Négatif pour la perception réglementaire et la stabilité de l'écosystème crypto, notamment pour les acteurs institutionnels.",
      "status": "intégré"
    }
  ],
  "levels_tonight": [
    {
      "asset": "BTC",
      "level": "64 000 $",
      "type": "resistance",
      "trigger": "Au-dessus de 64 000 $ : potentiel de continuation haussière vers 65 970 $."
    },
    {
      "asset": "BTC",
      "level": "62 900 $",
      "type": "support",
      "trigger": "Sous 62 900 $ : risque de retour vers le support majeur à 60 862 $."
    },
    {
      "asset": "ETH",
      "level": "1 833 $",
      "type": "resistance",
      "trigger": "Au-dessus de 1 833 $ : cible la résistance de Fibonacci à 1 892 $."
    },
    {
      "asset": "ETH",
      "level": "1 690 $",
      "type": "support",
      "trigger": "Sous 1 690 $ : invalidation du rebond, risque de test du support à 1 621 $."
    },
    {
      "asset": "DXY",
      "level": "101.00",
      "type": "resistance",
      "trigger": "Au-dessus de 101.00 : pression accrue sur les actifs risqués."
    },
    {
      "asset": "DXY",
      "level": "100.50",
      "type": "support",
      "trigger": "Sous 100.50 : allègement de la pression macro sur le marché crypto."
    },
    {
      "asset": "INJ",
      "level": "5.00 $",
      "type": "resistance",
      "trigger": "Au-dessus de 5.00 $ : continuation du momentum haussier court terme."
    },
    {
      "asset": "IMX",
      "level": "0.1450 $",
      "type": "resistance",
      "trigger": "Au-dessus de 0.1450 $ : signal de force pour les prochains jours."
    }
  ],
  "actions_tonight": [],
  "tomorrow_checklist": {
    "calendar": [
      {
        "label": "BOE Gov Bailey Speaks (UK)",
        "date": "2026-07-07",
        "when": "demain",
        "days_ahead": 1,
        "source": "ForexFactory",
        "importance": "medium",
        "weekday_label": "mardi",
        "date_label": "mardi 7 juillet",
        "time": "11:30"
      },
      {
        "label": "FOMC Meeting Minutes (US)",
        "date": "2026-07-08",
        "when": "dans 2j",
        "days_ahead": 2,
        "source": "ForexFactory",
        "importance": "high",
        "weekday_label": "mercredi",
        "date_label": "mercredi 8 juillet",
        "time": "19:00"
      }
    ],
    "checks": "Surveiller la réaction du marché aux commentaires de la BoE demain. Vérifier si BTC maintient son support à 62 900 $. Observer la persistance du rebond des actions tech US (AMD, COIN) pour confirmer un éventuel changement de sentiment.",
    "scenario": "Le marché crypto devrait consolider autour des niveaux actuels, avec une légère pression haussière si les actions US maintiennent leur élan et si le DXY continue de s'affaiblir.",
    "invalidation": "BTC clôture sous 62 000 $ ou le DXY repasse au-dessus de 101.50."
  },
  "blind_spots": "Les données sur les flux ETF restent indisponibles, limitant l'analyse des mouvements de capitaux institutionnels.",
  "footer": {
    "next_morning_time": "08h30",
    "next_report_at": "demain 08h30"
  },
  "expectancy": {
    "available": false,
    "sample": 0,
    "reason": "Espérance mathématique disponible dès 5 recos clôturées avec niveaux (actuellement 0)."
  },
  "daily_pnl": {
    "value_usd": 2756.26,
    "day_change_usd": 41.62,
    "day_change_pct": 1.53,
    "day_change_label": null,
    "top_movers": [
      {
        "symbol": "INJ",
        "change": 6.0,
        "pnl_usd": 2.99,
        "value_usd": 49.95
      },
      {
        "symbol": "IMX",
        "change": 5.2,
        "pnl_usd": 0.85,
        "value_usd": 16.44
      },
      {
        "symbol": "ACH",
        "change": 3.6,
        "pnl_usd": 0.6,
        "value_usd": 16.51
      },
      {
        "symbol": "JASMY",
        "change": 2.3,
        "pnl_usd": 1.5,
        "value_usd": 65.92
      },
      {
        "symbol": "ATOM",
        "change": 1.8,
        "pnl_usd": 0.46,
        "value_usd": 25.23
      }
    ]
  },
  "reco_bilan": [
    {
      "asset": "BTC",
      "action": "RENFORCER",
      "confidence": 80.0,
      "entry": 62861.0,
      "target": 64500.0,
      "current": 63661.0,
      "delta_pct": 1.27,
      "status": "on_track",
      "reason": "au-dessus de l'entrée · invalidé sous $60,861.88"
    },
    {
      "asset": "ETH",
      "action": "RENFORCER",
      "confidence": 80.0,
      "entry": 1765.06,
      "target": 1794.0,
      "current": 1791.45,
      "delta_pct": 1.5,
      "status": "on_track",
      "reason": "au-dessus de l'entrée · invalidé sous $1,621.30"
    },
    {
      "asset": "TAO",
      "action": "RENFORCER",
      "confidence": 75.0,
      "entry": 211.25,
      "target": 215.92,
      "current": 215.28,
      "delta_pct": 1.91,
      "status": "on_track",
      "reason": "au-dessus de l'entrée · invalidé sous $201.11"
    },
    {
      "asset": "RENDER",
      "action": "RENFORCER",
      "confidence": 75.0,
      "entry": 1.59,
      "target": 1.65,
      "current": 1.6,
      "delta_pct": 0.63,
      "status": "on_track",
      "reason": "au-dessus de l'entrée · invalidé sous $1.46"
    },
    {
      "asset": "LINK",
      "action": "RENFORCER",
      "confidence": 75.0,
      "entry": 7.93,
      "target": 8.14,
      "current": 8.01,
      "delta_pct": 1.01,
      "status": "on_track",
      "reason": "au-dessus de l'entrée · invalidé sous $7.34"
    },
    {
      "asset": "RSR",
      "action": "RENFORCER",
      "confidence": 75.0,
      "entry": 0.00119,
      "target": 0.001281,
      "current": 0.00122154,
      "delta_pct": 2.65,
      "status": "on_track",
      "reason": "au-dessus de l'entrée · invalidé sous $0.001067"
    }
  ],
  "polymarket_facts": {
    "fed_bars": {
      "cut_pct": 0.9,
      "hold_pct": 83.5,
      "hike_pct": 15.0,
      "dominant": "maintien",
      "dominant_pct": 83.5,
      "meeting_hint": "réunion juillet 2026"
    },
    "extra_markets": [
      {
        "question": "Strait of Hormuz traffic returns to normal by December 31?",
        "probability_pct": 64,
        "volume_usd": 4080450,
        "end_date": "2026-12-31T00:00:00Z"
      }
    ]
  },
  "since_morning_facts": {
    "available": true,
    "window_label": "depuis le matin (09h54)",
    "line": "BTC 62 861 $ → 63 661 $ (+1,3%) · ETH 1 765 $ → 1 791 $ (+1,5%) · F&G 24 → 24 (stable) · DXY 101.08 → 100.84 (−0,2%) · Fed maintien 89,5% → 83,5% (−6,0 pts)"
  },
  "derivatives_flows_line": "Funding BTC +0,007% · L/S 1,52",
  "levels_readout": {
    "BTC": "RSI 52 (neutre) · MACD haussier · Bollinger médiane · ATR 1,4% (≈866 $/j) · −4,2% vs MM50 · volume 7j +3% vs 30j",
    "ETH": "RSI 58 (neutre) · MACD haussier · Bollinger médiane · ATR 1,9% (≈34.04 $/j) · −0,6% vs MM50 · volume 7j −4% vs 30j"
  },
  "risk_score": {
    "score": 3.6,
    "level": "maîtrisé",
    "level_color": "#3B6D11",
    "factors": [
      "concentration L1 67%",
      "sentiment Peur Extrême (F&G 24)"
    ],
    "components": [
      {
        "label": "Drawdown 7j",
        "pts": 0.0,
        "max": 3.0
      },
      {
        "label": "Concentration",
        "pts": 2.4,
        "max": 2.5
      },
      {
        "label": "Volatilité 24h",
        "pts": 0.3,
        "max": 2.0
      },
      {
        "label": "Sentiment",
        "pts": 1.0,
        "max": 1.5
      }
    ],
    "dominant_axes": [
      {
        "label": "Concentration",
        "pts": 2.4,
        "max": 2.5,
        "ratio_pct": 96
      },
      {
        "label": "Sentiment",
        "pts": 1.0,
        "max": 1.5,
        "ratio_pct": 67
      }
    ],
    "holdings_snapshot": [
      "1000SATS",
      "ACH",
      "ADA",
      "ANKR",
      "AR",
      "ARB",
      "ATOM",
      "AXL",
      "BTC",
      "CFX",
      "CKB",
      "ETH",
      "FET",
      "GRT",
      "HBAR",
      "IMX",
      "INJ",
      "JASMY",
      "LINK",
      "NOT",
      "QNT",
      "RENDER",
      "RSR",
      "STX",
      "SXT",
      "TAO",
      "W",
      "XRP",
      "ZK"
    ]
  },
  "risk_score_readout": {
    "driver": "Score tiré par Concentration (2.4/2.5) et Sentiment (1.0/1.5).",
    "reco": "Diversifier hors du secteur dominant pour réduire la concentration.",
    "caveat": "Note indicative et déterministe (concentration, drawdown, volatilité, sentiment) : elle ne capte ni le risque spécifique projet ni les corrélations cachées ou chocs exogènes."
  },
  "risk_unchanged_since_morning": {
    "active": true,
    "morning_score": 3.6,
    "note": "Risque stable depuis ce matin (3.6/10 → 3.6/10) — composition du portefeuille inchangée."
  },
  "health_score": {
    "score": 3.2,
    "level": "à risque",
    "level_color": "#A32D2D",
    "axes": [
      {
        "label": "Diversification",
        "score": 1.6,
        "max": 10.0,
        "detail": "top secteur 67% du PTF"
      },
      {
        "label": "Momentum vs BTC",
        "score": 4.9,
        "max": 10.0,
        "detail": "-0.1 pts vs BTC 7j"
      },
      {
        "label": "Solidité (vs ATH)",
        "score": 3.0,
        "max": 10.0,
        "detail": "drawdown -67% vs ATH"
      }
    ],
    "driver": "Portée par Momentum vs BTC (4.9/10), pénalisée par Diversification (1.6/10).",
    "improve": "Alléger le secteur dominant sur rebond et étaler sur d'autres narratifs."
  },
  "health_unchanged_since_morning": {
    "active": true,
    "note": "Santé stable depuis ce matin (3.2/10 → 3.2/10) — composition du portefeuille inchangée."
  },
  "evening_macro": {
    "btc_price": 63661,
    "btc_change_24h": 1.4068766813823665,
    "eth_price": 1791.45,
    "eth_change_24h": 0.5452008195909932,
    "fear_greed": 24,
    "fear_greed_label": "Peur extrême",
    "fear_greed_delta": 0,
    "gold_usd": 4175.5,
    "gold_delta": 49.80000000000018,
    "sp500": 7546.38,
    "sp500_delta": 63.14000000000033,
    "nasdaq": 26141.887,
    "nasdaq_delta": 309.21500000000015,
    "vix": 15.7,
    "vix_delta": -0.11000000000000121,
    "brent_usd": 72.13,
    "brent_delta": 0.3299999999999983,
    "dxy": 100.845,
    "dxy_broad": 120.8866,
    "dxy_ice": 100.845,
    "dxy_delta": -0.012000000000000455,
    "nikkei": 69737.69,
    "nikkei_delta": -6.380000000004657,
    "stoxx50": 6398.01,
    "stoxx50_delta": -14.670000000000073,
    "eur_usd": 1.1444,
    "usd_jpy": 162.083,
    "ecb_deposit_rate": 2.25,
    "boj_rate": 0.727
  },
  "macro_source_status": {
    "gold_usd": "single",
    "brent_usd": "confirmed",
    "wti_usd": "confirmed",
    "sp500": "confirmed",
    "nasdaq": "confirmed",
    "vix": "confirmed",
    "us_10y": "confirmed",
    "dxy_ice": "single",
    "dxy": "single",
    "eur_usd": "confirmed",
    "usd_jpy": "confirmed",
    "nikkei": "confirmed",
    "stoxx50": "single",
    "dax": "single",
    "ecb_deposit_rate": "single",
    "boj_rate": "single"
  },
  "tomorrow_macro_events": [
    {
      "label": "BOE Gov Bailey Speaks (UK)",
      "date": "2026-07-07",
      "when": "demain",
      "days_ahead": 1,
      "source": "ForexFactory",
      "importance": "medium",
      "weekday_label": "mardi",
      "date_label": "mardi 7 juillet",
      "time": "11:30"
    },
    {
      "label": "FOMC Meeting Minutes (US)",
      "date": "2026-07-08",
      "when": "dans 2j",
      "days_ahead": 2,
      "source": "ForexFactory",
      "importance": "high",
      "weekday_label": "mercredi",
      "date_label": "mercredi 8 juillet",
      "time": "19:00"
    }
  ],
  "intraday_news": [
    {
      "title": "Judge revives fraud claim against Barry Silbert, DCG in Genesis Yield lawsuit",
      "source": "The Block",
      "timestamp": "19h55"
    },
    {
      "title": "Bitcoin needs trillions to go parabolic again as ETF demand fades",
      "source": "CryptoSlate",
      "timestamp": "18h00"
    },
    {
      "title": "Top Fed official backs new chair’s rethink of investor communications",
      "source": "Financial Times",
      "timestamp": "17h32"
    },
    {
      "title": "Russian-Sberbank Plans Crypto Wallet and Digital Depository by December",
      "source": "Bitcoin Magazine",
      "timestamp": "15h40"
    },
    {
      "title": "DeFi protocol Summer.fi halts Lazy Summer vaults after $6 million exploit",
      "source": "CoinDesk",
      "timestamp": "14h42"
    }
  ],
  "market_regime": {
    "available": true,
    "regime": "bear",
    "label_fr": "BAISSIER",
    "reasons": [
      "prix −14.8% vs MM200",
      "MM50 −10.7% vs MM200",
      "pente MM50 14j −7.4%"
    ],
    "price_vs_ma200_pct": -14.8,
    "ma50_vs_ma200_pct": -10.7,
    "ma50_slope_14d_pct": -7.4,
    "since": "2026-07-06",
    "changed": false,
    "days_in_regime": 0
  },
  "_saved_at": "2026-07-06T19:04:05.263437+00:00"
}