{
  "header": {
    "title": "Veille crypto",
    "subtitle": "rapport dégradé",
    "date": "lundi 8 juin 2026 · 20:01 Casablanca",
    "time_casablanca": "lundi 8 juin 2026 · 20:01 Casablanca",
    "hours_since_morning": 12,
    "ptf_value_delta_since_morning": -3.16,
    "ptf_value_pct_since_morning": -0.18
  },
  "_degraded": true,
  "footer": {
    "note": "Quota IA épuisé. Données brutes disponibles.",
    "next_report_at": "demain 08h30"
  },
  "delta_of_the_day": [
    "⚠️ Quota IA épuisé."
  ],
  "portfolio_snapshot": {
    "change_since_morning_pct": -0.18,
    "value_usd": 1739.09
  },
  "daily_pnl": {
    "value_usd": 1739.09,
    "day_change_usd": -3.16,
    "day_change_pct": -0.18,
    "top_movers": [
      {
        "symbol": "INJ",
        "change": 10.2,
        "pnl_usd": 5.98,
        "value_usd": 58.85
      },
      {
        "symbol": "ATOM",
        "change": 6.4,
        "pnl_usd": 1.81,
        "value_usd": 28.04
      },
      {
        "symbol": "IMX",
        "change": 6.1,
        "pnl_usd": 1.0,
        "value_usd": 16.44
      },
      {
        "symbol": "TAO",
        "change": 5.3,
        "pnl_usd": 18.51,
        "value_usd": 349.78
      },
      {
        "symbol": "ETH",
        "change": 3.9,
        "pnl_usd": 11.58,
        "value_usd": 295.33
      }
    ]
  },
  "evening_macro": {
    "sp500": 7420.55,
    "sp500_delta": -200.57,
    "nasdaq": 25987.676,
    "nasdaq_delta": -1121.53,
    "dxy": 100.001,
    "dxy_broad": 118.8783,
    "dxy_ice": 100.001
  },
  "macro_source_status": {
    "gold_usd": "single",
    "brent_usd": "confirmed",
    "wti_usd": "confirmed",
    "sp500": "confirmed",
    "nasdaq": "confirmed",
    "vix": "single",
    "us_10y": "single",
    "dxy_ice": "single",
    "dxy": "single",
    "eur_usd": "confirmed",
    "usd_jpy": "confirmed"
  },
  "intraday_news": [
    {
      "title": "India’s central bank details forex swap facility guidelines",
      "source": "Investing.com",
      "timestamp": "2026-06-08T18:36:34+00:00"
    },
    {
      "title": "FTX Founder Sam Bankman-Fried Has Formally Filed for a Pardon From President Trump",
      "source": "Decrypt",
      "timestamp": "2026-06-08T18:08:19+00:00"
    },
    {
      "title": "Sam Bankman-Fried seeks Trump pardon",
      "source": "Financial Times",
      "timestamp": "2026-06-08T17:19:13+00:00"
    },
    {
      "title": "Sam Bankman-Fried Formally Seeks Presidential Pardon From Trump, Files Clemency Petition",
      "source": "Bitcoin Magazine",
      "timestamp": "2026-06-08T16:54:03+00:00"
    },
    {
      "title": "Israel and Iran halt counterstrikes",
      "source": "Financial Times",
      "timestamp": "2026-06-08T16:41:48+00:00"
    }
  ],
  "_saved_at": "2026-06-08T19:01:54.865138+00:00"
}